MANIFEST.in
README.rst
setup.cfg
setup.py
migration/__init__.py
migration/manage.py
migration/versions/001_initial_schema.py
migration/versions/002_add_stock_and_shiptime.py
migration/versions/__init__.py
stroller/__init__.py
stroller/helpers.py
stroller.egg-info/PKG-INFO
stroller.egg-info/SOURCES.txt
stroller.egg-info/dependency_links.txt
stroller.egg-info/entry_points.txt
stroller.egg-info/not-zip-safe
stroller.egg-info/requires.txt
stroller.egg-info/top_level.txt
stroller/controllers/__init__.py
stroller/controllers/ecommerce.py
stroller/controllers/manage.py
stroller/controllers/payment.py
stroller/controllers/widgets.py
stroller/lib/__init__.py
stroller/lib/cart.py
stroller/lib/paypal.py
stroller/model/__init__.py
stroller/model/commerce.py
stroller/model/core.py
stroller/static/__init__.py
stroller/static/cancel.png
stroller/static/cart.png
stroller/static/checkout.png
stroller/static/clone.png
stroller/static/confirm.css
stroller/static/delete.png
stroller/static/edit.png
stroller/static/featured.png
stroller/static/featured_rm.png
stroller/static/folder.png
stroller/static/list.png
stroller/static/manage.css
stroller/static/style.css
stroller/templates/__init__.py
stroller/templates/cart.html
stroller/templates/category.html
stroller/templates/featured.html
stroller/templates/index.html
stroller/templates/product.html
stroller/templates/recap.html
stroller/templates/search.html
stroller/templates/stroller_commons.html
stroller/templates/manage/__init__.py
stroller/templates/manage/form.html
stroller/templates/manage/orderedit.html
stroller/templates/manage/orderedproducts.html
stroller/templates/manage/orderlist.html
stroller/templates/manage/ordershow.html
stroller/templates/manage/usermanage.html
stroller/templates/payment/__init__.py
stroller/templates/payment/confirm.html