Metadata-Version: 1.1
Name: stroller
Version: 0.4.1
Summary: E-commerce Application and Library for TurboGears2
Home-page: https://bitbucket.org/_amol_/stroller
Author: AXANT
Author-email: tech@axant.it
License: GPL
Keywords: turbogears2.application turbogears2.extension ecommerce paypal shop
Platform: UNKNOWN
Classifier: Development Status :: 5 - Production/Stable
Classifier: Framework :: TurboGears
Classifier: Topic :: Office/Business :: Financial :: Point-Of-Sale
Classifier: Topic :: Internet :: WWW/HTTP :: Dynamic Content
